scgraph_data/__init__.py
scgraph_data/world_highways.py
scgraph_data/world_highways_and_marnet.py
scgraph_data/world_railways.py
scgraph_data-2.0.0.dist-info/LICENSE
scgraph_data-2.0.0.dist-info/METADATA
scgraph_data-2.0.0.dist-info/WHEEL
scgraph_data-2.0.0.dist-info/top_level.txt
scgraph_data-2.0.0.dist-info/RECORD
