Metadata-Version: 2.1
Name: scgraph_data
Version: 2.0.0
Summary: Large geograph data for the scgraph package.
Author-email: Connor Makowski <conmak@mit.edu>
Project-URL: Homepage, https://github.com/connor-makowski/scgraph_data
Project-URL: Bug Tracker, https://github.com/connor-makowski/scgraph_data/issues
Classifier: Programming Language :: Python :: 3
Classifier: License :: OSI Approved :: MIT License
Classifier: Operating System :: OS Independent
Requires-Python: >=3.6
License-File: LICENSE
Requires-Dist: scgraph>=2.0.0
